README.rst
setup.cfg
setup.py
pysatadif/__init__.py
pysatadif/__main__.py
pysatadif/argsc.py
pysatadif/pysatadif.py
pysatical.egg-info/PKG-INFO
pysatical.egg-info/SOURCES.txt
pysatical.egg-info/dependency_links.txt
pysatical.egg-info/entry_points.txt
pysatical.egg-info/requires.txt
pysatical.egg-info/top_level.txt