Metadata-Version: 1.1
Name: pysatical
Version: 0.0.1
Summary: Simple utility to generate proper ADIF for satellite contacts
Home-page: https://github.com/jeremymturner/pysatadif
Author: Jeremy Turner
Author-email: jeremy@jeremymturner.com
License: Apache
Keywords: hamradio satellites adif
Platform: UNKNOWN
Classifier: Development Status :: 4 - Beta
Classifier: Environment :: Console
Classifier: Intended Audience :: Science/Research
Classifier: Operating System :: OS Independent
Classifier: License :: OSI Approved :: Apache Software License
Classifier: Programming Language :: Python :: 2
Classifier: Programming Language :: Python :: 2.7
Classifier: Programming Language :: Python :: 3
Classifier: Programming Language :: Python :: 3.3
Classifier: Programming Language :: Python :: 3.4
Classifier: Programming Language :: Python :: 3.5
Classifier: Programming Language :: Python :: 3.6
Classifier: Programming Language :: Python :: 3.7
